instructlab/dolomite/__init__.py
instructlab/dolomite/_version.py
instructlab/dolomite/enums.py
instructlab/dolomite/hf_models/__init__.py
instructlab/dolomite/hf_models/config.py
instructlab/dolomite/hf_models/defaults.py
instructlab/dolomite/hf_models/enums.py
instructlab/dolomite/hf_models/register_hf.py
instructlab/dolomite/hf_models/utils.py
instructlab/dolomite/hf_models/mixins/__init__.py
instructlab/dolomite/hf_models/mixins/dense/__init__.py
instructlab/dolomite/hf_models/mixins/dense/base.py
instructlab/dolomite/hf_models/mixins/dense/main.py
instructlab/dolomite/hf_models/mixins/dense_TP/__init__.py
instructlab/dolomite/hf_models/mixins/dense_TP/base.py
instructlab/dolomite/hf_models/mixins/dense_TP/main.py
instructlab/dolomite/hf_models/mixins/moe/__init__.py
instructlab/dolomite/hf_models/mixins/moe/base.py
instructlab/dolomite/hf_models/mixins/moe/main.py
instructlab/dolomite/hf_models/mixins/moe_TP/__init__.py
instructlab/dolomite/hf_models/mixins/moe_TP/base.py
instructlab/dolomite/hf_models/mixins/moe_TP/main.py
instructlab/dolomite/hf_models/model_conversion/__init__.py
instructlab/dolomite/hf_models/model_conversion/bigcode.py
instructlab/dolomite/hf_models/model_conversion/granite.py
instructlab/dolomite/hf_models/model_conversion/granitemoe.py
instructlab/dolomite/hf_models/model_conversion/llama.py
instructlab/dolomite/hf_models/modeling_utils/__init__.py
instructlab/dolomite/hf_models/modeling_utils/embedding.py
instructlab/dolomite/hf_models/modeling_utils/linear.py
instructlab/dolomite/hf_models/modeling_utils/activations/__init__.py
instructlab/dolomite/hf_models/modeling_utils/activations/base.py
instructlab/dolomite/hf_models/modeling_utils/activations/glu.py
instructlab/dolomite/hf_models/modeling_utils/attention/__init__.py
instructlab/dolomite/hf_models/modeling_utils/attention/base.py
instructlab/dolomite/hf_models/modeling_utils/attention/flash.py
instructlab/dolomite/hf_models/modeling_utils/attention/padding_free.py
instructlab_dolomite-0.2.0.dist-info/LICENSE
instructlab_dolomite-0.2.0.dist-info/METADATA
instructlab_dolomite-0.2.0.dist-info/WHEEL
instructlab_dolomite-0.2.0.dist-info/top_level.txt
instructlab_dolomite-0.2.0.dist-info/RECORD
