Metadata-Version: 2.1
Name: instructlab-dolomite
Version: 0.2.0
Summary: Dolomite Engine
Author-email: InstructLab <dev@instructlab.ai>
License: Apache-2.0
Project-URL: homepage, https://instructlab.ai
Project-URL: source, https://github.com/instructlab/GPTDolomite
Project-URL: issues, https://github.com/instructlab/GPTDolomite/issues
Classifier: Development Status :: 3 - Alpha
Classifier: Environment :: Console
Classifier: License :: OSI Approved :: Apache Software License
Classifier: License :: OSI Approved :: MIT License
Classifier: Operating System :: MacOS :: MacOS X
Classifier: Operating System :: POSIX :: Linux
Classifier: Topic :: Scientific/Engineering :: Artificial Intelligence
Classifier: Programming Language :: Python :: 3
Classifier: Programming Language :: Python :: 3.10
Classifier: Programming Language :: Python :: 3.11
Classifier: Programming Language :: Python :: 3.12
Classifier: Programming Language :: Python :: Implementation :: CPython
Requires-Python: >=3.10
License-File: LICENSE
Requires-Dist: torch
Requires-Dist: transformers>=4.40.0
Requires-Dist: safetensors
